uwsgi_sloth/__init__.py
uwsgi_sloth/analyzer.py
uwsgi_sloth/compat.py
uwsgi_sloth/models.py
uwsgi_sloth/sample.conf
uwsgi_sloth/settings.py
uwsgi_sloth/structures.py
uwsgi_sloth/tailer.py
uwsgi_sloth/template.py
uwsgi_sloth/utils.py
uwsgi_sloth/commands/__init__.py
uwsgi_sloth/commands/analyze.py
uwsgi_sloth/commands/echo_conf.py
uwsgi_sloth/commands/start.py
uwsgi_sloth/templates/macros.html
uwsgi_sloth/templates/realtime.html
uwsgi_sloth/templates/report.html
uwsgi_sloth/tests/__init__.py
uwsgi_sloth/tests/test_analyzer.py
uwsgi_sloth/tests/test_structures.py
uwsgi_sloth-3.0.1.data/scripts/uwsgi-sloth
uwsgi_sloth-3.0.1.dist-info/LICENSE
uwsgi_sloth-3.0.1.dist-info/METADATA
uwsgi_sloth-3.0.1.dist-info/WHEEL
uwsgi_sloth-3.0.1.dist-info/top_level.txt
uwsgi_sloth-3.0.1.dist-info/RECORD
