Metadata-Version: 2.1
Name: uwsgi-sloth
Version: 3.0.1
Summary: A simple uwsgi access log analyzer
Home-page: https://github.com/piglei/uwsgi-sloth
Author: piglei
Author-email: piglei2007@gmail.com
License: Apache License, Version 2.0
Keywords: uwsgi log analyzer
Platform: UNKNOWN
Classifier: Programming Language :: Python :: 3
Requires-Dist: jinja2
Requires-Dist: configobj
